sinli/__init__.py
sinli/document.py
sinli/line.py
sinli/subject.py
sinli/common/__init__.py
sinli/common/encoded_values.py
sinli/doctype/__init__.py
sinli/doctype/abono/__init__.py
sinli/doctype/abono/v2.py
sinli/doctype/devolu/__init__.py
sinli/doctype/devolu/v2.py
sinli/doctype/devolu/v3.py
sinli/doctype/envio/__init__.py
sinli/doctype/envio/v8.py
sinli/doctype/factul/__init__.py
sinli/doctype/factul/v1.py
sinli/doctype/libros/__init__.py
sinli/doctype/libros/v10.py
sinli/doctype/libros/v8.py
sinli/doctype/libros/v9.py
sinli/doctype/liqve2/__init__.py
sinli/doctype/liqve2/v2.py
sinli/doctype/mensaj/__init__.py
sinli/doctype/mensaj/v1.py
sinli/doctype/pedido/__init__.py
sinli/doctype/pedido/v7.py
sinli-1.4.0.dist-info/licenses/LICENSE
sinli-1.4.0.dist-info/METADATA
sinli-1.4.0.dist-info/WHEEL
sinli-1.4.0.dist-info/top_level.txt
sinli-1.4.0.dist-info/RECORD
