Metadata-Version: 2.4
Name: sinli
Version: 1.4.0
Summary: Implementation of the SINLI format. It is used in the book sector in Spain to express commercial operations between book sellers, distributors and editors
Author-email: Devcontrol <devcontrol@sindominio.net>
License:                     GNU AFFERO GENERAL PUBLIC LICENSE
Classifier: Programming Language :: Python :: 3
Classifier: Topic :: Scientific/Engineering :: Interface Engine/Protocol Translator
Requires-Python: >=3.7
License-File: LICENSE
Requires-Dist: typing-extensions==4.7.1
Requires-Dist: pycountry==22.3.5
Requires-Dist: pytest
Dynamic: license-file
